LICENSE
scifin/__init__.py
scifin/classifier/__init__.py
scifin/classifier/classifier.py
scifin/exceptions/__init__.py
scifin/exceptions/errors.py
scifin/exceptions/exceptions.py
scifin/fouriertrf/__init__.py
scifin/fouriertrf/fouriertrf.py
scifin/geneticalg/__init__.py
scifin/geneticalg/geneticalg.py
scifin/marketdata/__init__.py
scifin/marketdata/marketdata.py
scifin/marketdata/simuldata.py
scifin/montecarlo/__init__.py
scifin/montecarlo/montecarlo.py
scifin/neuralnets/__init__.py
scifin/neuralnets/neuralnets.py
scifin/statistics/__init__.py
scifin/statistics/distributions.py
scifin/statistics/statistics.py
scifin/timeseries/__init__.py
scifin/timeseries/randomseries.py
scifin/timeseries/timeseries.py
scifin-0.1.0.dist-info/entry_points.txt
scifin-0.1.0.dist-info/LICENSE
scifin-0.1.0.dist-info/WHEEL
scifin-0.1.0.dist-info/METADATA
scifin-0.1.0.dist-info/RECORD
