Metadata-Version: 2.1
Name: scifin
Version: 0.1.0
Summary: SciFin is a python package for Science and Finance.
Home-page: https://github.com/SciFin-Team/SciFin
License: MIT
Keywords: SciFin,scifin,science,finance
Author: Fabien Nugier
Author-email: fabien.nugier@outlook.com
Requires-Python: >=3.6.1,<4.0.0
Classifier: Environment :: Console
Classifier: Intended Audience :: Education
Classifier: Intended Audience :: Financial and Insurance Industry
Classifier: Intended Audience :: Science/Research
Classifier: License :: OSI Approved :: MIT License
Classifier: Operating System :: OS Independent
Classifier: Programming Language :: Python
Classifier: Programming Language :: Python :: 3
Classifier: Programming Language :: Python :: 3.7
Classifier: Programming Language :: Python :: 3.8
Classifier: Topic :: Software Development :: Build Tools
Requires-Dist: IPython (>=7.13.0,<8.0.0)
Requires-Dist: matplotlib (>=3.1.3,<4.0.0)
Requires-Dist: numpy (>=1.18.1,<2.0.0)
Requires-Dist: pandas (<=1.0.3)
Requires-Dist: pandas_datareader (>=0.8.1,<0.9.0)
Requires-Dist: pytz (>=2019.3,<2020.0)
Requires-Dist: requests (>=2.23.0,<3.0.0)
Requires-Dist: scikit-learn (>=0.23.0,<0.24.0)
Requires-Dist: scipy (>=1.4.1,<2.0.0)
Requires-Dist: statsmodels (>=0.11.0,<0.12.0)
Project-URL: Documentation, https://github.com/SciFin-Team/SciFin/wiki
Project-URL: Repository, https://github.com/SciFin-Team/SciFin
